trading_calendar/__init__.py
trading_calendar/trading_calendar.py
trading_calendar_szse-1.0.0.dist-info/METADATA
trading_calendar_szse-1.0.0.dist-info/WHEEL
trading_calendar_szse-1.0.0.dist-info/top_level.txt
trading_calendar_szse-1.0.0.dist-info/RECORD
