Metadata-Version: 2.4
Name: trading-calendar-szse
Version: 1.0.0
Summary: 深交所交易日历Python接口
Home-page: https://github.com/yourusername/trading-calendar-szse
Author: 忍冬
Classifier: Programming Language :: Python :: 3
Classifier: License :: OSI Approved :: MIT License
Classifier: Operating System :: OS Independent
Requires-Python: >=3.6
Requires-Dist: requests>=2.0.0
Dynamic: author
Dynamic: classifier
Dynamic: description
Dynamic: description-content-type
Dynamic: home-page
Dynamic: requires-dist
Dynamic: requires-python
Dynamic: summary
